logbrain/__init__.py
logbrain/logbrain.py
logbrain-0.1.2.dist-info/licenses/LICENSE
tests/__init__.py
tests/test_logbrain.py
logbrain-0.1.2.dist-info/METADATA
logbrain-0.1.2.dist-info/WHEEL
logbrain-0.1.2.dist-info/top_level.txt
logbrain-0.1.2.dist-info/RECORD
