Metadata-Version: 2.4
Name: logbrain
Version: 0.1.2
Summary: LogBrain - Smart log analyzer using symbolic logic and lightweight AI
Home-page: https://github.com/catchmaurya/logbrain
Author: Maurya Allimuthu
Author-email: catchmaurya@gmail.com
License: MIT
Classifier: Programming Language :: Python :: 3
Classifier: Operating System :: OS Independent
Classifier: License :: OSI Approved :: MIT License
License-File: LICENSE
Requires-Dist: transformers
Requires-Dist: pytesseract
Requires-Dist: Pillow
Requires-Dist: requests
Dynamic: author
Dynamic: author-email
Dynamic: classifier
Dynamic: description
Dynamic: description-content-type
Dynamic: home-page
Dynamic: license
Dynamic: license-file
Dynamic: requires-dist
Dynamic: summary
